agentex/__init__.py
agentex/agent.py
agentex/central_hub.py
agentex/swarm.py
agentex/logging/logger.py
agentex/tasks/__init__.py
agentex/tasks/async_task.py
agentex/tasks/base_task.py
agentex/tasks/sync_task.py
agentex/tests/communication_test.py
agentex/tests/news_agent.py
agentex/tests/sample.txt
agentex/tests/test.py
agentex-0.0.8.dist-info/METADATA
agentex-0.0.8.dist-info/WHEEL
agentex-0.0.8.dist-info/RECORD
