Metadata-Version: 2.4
Name: agentex
Version: 0.0.8
Summary: A multi-agent asynchronous framework for swarm communication and task execution.
Project-URL: Homepage, https://github.com/onedavidwilliams/AgentEx
Project-URL: Source, https://github.com/onedavidwilliams/AgentEx
Project-URL: Issues, https://github.com/onedavidwilliams/AgentEx/issues
Author-email: David Williams <deltaflyerguy5@gmail.com>
License: GPL-3.0-or-later
Keywords: AI,asynchronous,framework,multi-agent,swarm,tasks
Classifier: Development Status :: 3 - Alpha
Classifier: Intended Audience :: Developers
Classifier: License :: OSI Approved :: GNU General Public License v3 (GPLv3)
Classifier: Operating System :: OS Independent
Classifier: Programming Language :: Python :: 3
Classifier: Programming Language :: Python :: 3.8
Classifier: Programming Language :: Python :: 3.9
Classifier: Topic :: Software Development :: Libraries :: Application Frameworks
Requires-Python: >=3.8
Requires-Dist: aiohttp>=3.8.0
Requires-Dist: exlog
Requires-Dist: feedparser
Requires-Dist: textblob
Provides-Extra: dev
Requires-Dist: pytest; extra == 'dev'
Requires-Dist: pytest-asyncio; extra == 'dev'
Provides-Extra: docs
Requires-Dist: mkdocs; extra == 'docs'
Requires-Dist: mkdocs-material; extra == 'docs'
Provides-Extra: test
Requires-Dist: coverage; extra == 'test'
Requires-Dist: pytest-cov; extra == 'test'
